safe_print_utils/__init__.py
safe_print_utils/safe_print_utils.py
tests/__init__.py
tests/test_safe_print.py
safe_print_utils-0.1.1.dist-info/LICENSE.txt
safe_print_utils-0.1.1.dist-info/METADATA
safe_print_utils-0.1.1.dist-info/WHEEL
safe_print_utils-0.1.1.dist-info/top_level.txt
safe_print_utils-0.1.1.dist-info/RECORD
