Metadata-Version: 2.1
Name: safe-print-utils
Version: 0.1.1
Summary: A utility for safely printing with optional color formatting and logging to file.
Home-page: https://github.com/syntaxsurge/safe_print_utils
Author: SyntaxSurge
Author-email: syntaxsurge@gmail.com
License: MIT
Classifier: Programming Language :: Python :: 3
Classifier: License :: OSI Approved :: MIT License
License-File: LICENSE.txt
Requires-Dist: colorama
